{
	"permissions": [
		{
			"value": "1",
			"name": "Manage Users"
		}, {
			"value": "2",
			"name": "Manage Roles"
		}, {
			"value": "3",
			"name": "Manage Permissions"
		}, {
			"value": "4",
			"name": "Manage Hotels"
		}, {
			"value": "5",
			"name": "Manage Guests"
		}, {
			"value": "6",
			"name": "Manage Events"
		},  {
			"value": "7",
			"name": "Manage Chains"
		}, {
			"value": "8",
			"name": "Manage Hotel Room"
		}, {
			"value": "9",
			"name": "Respond to messages"
		}
	],



	"roles": [
		{
			"value": "3",
			"name": "HOTEL ADMIN",
			"is_hotel_admin": "true",
			"assigned_permissions": ["1","2","3", "8"]
		}, {
			"value": "12",
			"name": "HOTEL STAFF",
			"is_hotel_admin": "false",
			"assigned_permissions": ["1","2","3"]
		}, {
			"value": "13",
			"name": "MODERATOR",
			"is_hotel_admin": "false",
			"assigned_permissions": ["1", "2","8","9","4","5"]
		},
		{
			"value": "15",
			"name": "FLOOR KEEPER",
			"is_hotel_admin": "false",
			"assigned_permissions": ["3", "8"]
		}
	]
}